<?xml version="1.0" encoding="UTF-8"?>
<!--
  ~ Sakuli - Testing and Monitoring-Tool for Websites and common UIs.
  ~
  ~ Copyright 2013 - 2014 the original author or authors.
  ~
  ~ Licensed under the Apache License, Version 2.0 (the "License");
  ~ you may not use this file except in compliance with the License.
  ~ You may obtain a copy of the License at
  ~
  ~     http://www.apache.org/licenses/LICENSE-2.0
  ~
  ~ Unless required by applicable law or agreed to in writing, software
  ~ distributed under the License is distributed on an "AS IS" BASIS,
  ~ WITHOUT WARRANTIES OR CONDITIONS OF ANY KIND, either express or implied.
  ~ See the License for the specific language governing permissions and
  ~ limitations under the License.
  -->

<configuration scan="true">

    <appender name="sakuli" class="ch.qos.logback.core.rolling.RollingFileAppender">
        <!--See also http://logback.qos.ch/manual/appenders.html#RollingFileAppender-->
        <File>${sakuli.log.folder}/_sakuli.log</File>
        <encoder>
            <pattern>${sakuli.log.pattern}</pattern>
        </encoder>
        <rollingPolicy class="ch.qos.logback.core.rolling.FixedWindowRollingPolicy">
            <maxIndex>10</maxIndex>
            <FileNamePattern>${sakuli.log.folder}/_sakuli.log.%i</FileNamePattern>
        </rollingPolicy>
        <triggeringPolicy class="ch.qos.logback.core.rolling.SizeBasedTriggeringPolicy">
            <MaxFileSize>10000KB</MaxFileSize>
        </triggeringPolicy>
    </appender>
    <appender name="stdout" class="ch.qos.logback.core.ConsoleAppender">
        <encoder>
            <pattern>${sakuli.log.pattern}</pattern>
        </encoder>
    </appender>

    <!-- fix configured log levels-->
    <logger name="uk.org.lidalia.sysoutslf4j.context.SysOutOverSLF4J" level="WARN"/>
    <logger name="org.apache.commons" level="WARN"/>


    <!-- default level INFO; to set the logging level over command line add e.g. '-Dlog-level-sakuli=DEBUG' -->
    <logger name="org.sakuli" level="${log-level-sakuli:-INFO}"/>

    <!-- default level WARN; to set the logging level over command line add e.g. '-Dlog-level-sikuli=INFO' -->
    <logger name="org.sikuli" level="${log-level-sikuli:-WARN}"/>

    <!-- default level WARN; to set the logging level over command line add e.g. '-Dlog-level-sahi=INFO' -->
    <logger name="net.sf.sahi" level="${log-level-sahi:-WARN}"/>

    <!-- default level WARN; to set the logging level over command line add e.g. '-Dlog-level-spring=INFO' -->
    <logger name="org.springframework" level="${log-level-spring:-WARN}"/>

    <!-- default level INFO; to set the logging level over command line add e.g. '-Dlog-level-root=DEBUG' -->
    <root level="${log-level-root:-INFO}">
        <appender-ref ref="stdout"/>
        <appender-ref ref="sakuli"/>
    </root>

</configuration>